sageml/__init__.py
sageml/__main__.py
sageml/sageml.py
sageml/sageml_experimental.py
sageml/algorithms/__init__.py
sageml/algorithms/neural_network.py
sageml/algorithms/random_guessing.py
sageml/algorithms/scikit_algorithms.py
sageml/algorithms/xg_boost.py
sageml/base/__init__.py
sageml/base/model.py
sageml/base/preprocess.py
sageml/base/evaluation/__init__.py
sageml/base/evaluation/evaluator.py
sageml/dev/__init__.py
sageml/dev/__main__.py
sageml/dev/functions.py
sageml/hpo/__init__.py
sageml/hpo/hyperparameter_tuning.py
sageml/hpo/sklearn_param_extraction.py
sageml/interface/__init__.py
sageml/interface/items.py
sageml/interface/tutorial.py
sageml/interface/welcome.py
sageml/meta_learning/__init__.py
sageml/meta_learning/meta_model_search.py
sageml/meta_learning/model_architecture.py
sageml/meta_learning/dataset_parameters/__init__.py
sageml/meta_learning/dataset_parameters/base.py
sageml/meta_learning/dataset_parameters/sota.py
sageml/meta_learning/dataset_parameters/statistical.py
sageml/meta_learning/dataset_parameters/topological.py
sageml/meta_learning/model_prediction/__init__.py
sageml/meta_learning/model_prediction/model_prediction.py
sageml/preprocessing/__init__.py
sageml/preprocessing/combined.py
sageml/preprocessing/encoder.py
sageml/preprocessing/nan_imputer.py
sageml/preprocessing/normalizer.py
sageml/preprocessing/sota.py
sageml/preprocessing/standardizer.py
sageml/preprocessing/type_inferer.py
sageml/preprocessing/variance_selector.py
sageml/utils/__init__.py
sageml/utils/options.py
sageml/utils/profiling.py
sageml/utils/timing.py
sageml/utils/error_tools/__init__.py
sageml/utils/error_tools/exceptions.py
sageml/utils/error_tools/workflow_validation.py
sageml/workflow/__init__.py
sageml/workflow/__main__.py
sageml/workflow/algorithms_evaluations.py
sageml/workflow/extract_parameters.py
sageml/workflow/train_model.py
sageml/workflow/utils.py
sageml-0.2.0.dist-info/licenses/LICENSE
sageml-0.2.0.dist-info/METADATA
sageml-0.2.0.dist-info/WHEEL
sageml-0.2.0.dist-info/entry_points.txt
sageml-0.2.0.dist-info/top_level.txt
sageml-0.2.0.dist-info/RECORD
