Metadata-Version: 2.4
Name: sageml
Version: 0.2.0
Summary: SageML is library for automatic one-shot algorithm selection for tabular data using tda for extracting information about dataset.
Author-email: Dawid64 <dawid.siera@gmail.com>, Tole-k <anatol.kaczmarek@gmail.com>
License: LICENSE
Requires-Python: >=3.13
License-File: LICENSE
Requires-Dist: certifi>=2025.4.26
Requires-Dist: ipykernel>=6.30.1
Requires-Dist: matplotlib>=3.10.1
Requires-Dist: numpy>=2.2.5
Requires-Dist: optuna>=4.3.0
Requires-Dist: pandas>=2.2.3
Requires-Dist: pyballmapper>=0.3.7
Requires-Dist: requests>=2.32.3
Requires-Dist: ripser>=0.6.12
Requires-Dist: scikit-learn>=1.6.1
Requires-Dist: scikit-posthocs>=0.11.4
Requires-Dist: torch>=2.7.0
Requires-Dist: tqdm>=4.67.1
Requires-Dist: xgboost>=3.0.0
Dynamic: license-file
